NanjingdaxueJisuanjikexueYuJishuXiJisuanjixitongJichuKechengShiyan2021Fix1/README.md
NanjingdaxueJisuanjikexueYuJishuXiJisuanjixitongJichuKechengShiyan2021Fix1/__init__.py
NanjingdaxueJisuanjikexueYuJishuXiJisuanjixitongJichuKechengShiyan2021Fix1/__main__.py
NanjingdaxueJisuanjikexueYuJishuXiJisuanjixitongJichuKechengShiyan2021Fix1/file.epub
NanjingdaxueJisuanjikexueYuJishuXiJisuanjixitongJichuKechengShiyan2021Fix1/index.html
NanjingdaxueJisuanjikexueYuJishuXiJisuanjixitongJichuKechengShiyan2021Fix1/css/__init__.py
NanjingdaxueJisuanjikexueYuJishuXiJisuanjixitongJichuKechengShiyan2021Fix1/css/annotations.css
NanjingdaxueJisuanjikexueYuJishuXiJisuanjixitongJichuKechengShiyan2021Fix1/css/main.css
NanjingdaxueJisuanjikexueYuJishuXiJisuanjixitongJichuKechengShiyan2021Fix1/css/normalize.css
NanjingdaxueJisuanjikexueYuJishuXiJisuanjixitongJichuKechengShiyan2021Fix1/css/popup.css
NanjingdaxueJisuanjikexueYuJishuXiJisuanjixitongJichuKechengShiyan2021Fix1/font/__init__.py
NanjingdaxueJisuanjikexueYuJishuXiJisuanjixitongJichuKechengShiyan2021Fix1/font/fontello.eot
NanjingdaxueJisuanjikexueYuJishuXiJisuanjixitongJichuKechengShiyan2021Fix1/font/fontello.svg
NanjingdaxueJisuanjikexueYuJishuXiJisuanjixitongJichuKechengShiyan2021Fix1/font/fontello.ttf
NanjingdaxueJisuanjikexueYuJishuXiJisuanjixitongJichuKechengShiyan2021Fix1/font/fontello.woff
NanjingdaxueJisuanjikexueYuJishuXiJisuanjixitongJichuKechengShiyan2021Fix1/img/__init__.py
NanjingdaxueJisuanjikexueYuJishuXiJisuanjixitongJichuKechengShiyan2021Fix1/img/annotator-glyph-sprite.png
NanjingdaxueJisuanjikexueYuJishuXiJisuanjixitongJichuKechengShiyan2021Fix1/img/annotator-icon-sprite.png
NanjingdaxueJisuanjikexueYuJishuXiJisuanjixitongJichuKechengShiyan2021Fix1/img/apple-touch-icon.png
NanjingdaxueJisuanjikexueYuJishuXiJisuanjixitongJichuKechengShiyan2021Fix1/img/cancelfullscreen.png
NanjingdaxueJisuanjikexueYuJishuXiJisuanjixitongJichuKechengShiyan2021Fix1/img/close.png
nanjingdaxue_jisuanjikexue_yu_jishu_xi_jisuanjixitong_jichu_kecheng_shiyan_2021_fix1-2025.3.25.0.dist-info/METADATA
nanjingdaxue_jisuanjikexue_yu_jishu_xi_jisuanjixitong_jichu_kecheng_shiyan_2021_fix1-2025.3.25.0.dist-info/WHEEL
nanjingdaxue_jisuanjikexue_yu_jishu_xi_jisuanjixitong_jichu_kecheng_shiyan_2021_fix1-2025.3.25.0.dist-info/entry_points.txt
nanjingdaxue_jisuanjikexue_yu_jishu_xi_jisuanjixitong_jichu_kecheng_shiyan_2021_fix1-2025.3.25.0.dist-info/top_level.txt
nanjingdaxue_jisuanjikexue_yu_jishu_xi_jisuanjixitong_jichu_kecheng_shiyan_2021_fix1-2025.3.25.0.dist-info/RECORD
